anki_export/__init__.py
anki_export/app.py
anki_export-0.1.4.dist-info/LICENSE
anki_export-0.1.4.dist-info/WHEEL
anki_export-0.1.4.dist-info/METADATA
anki_export-0.1.4.dist-info/RECORD
