Metadata-Version: 2.1
Name: anki-export
Version: 0.1.4
Summary: Export your Anki *.apkg to Python. Read Anki *.apkg in Python.
License: MIT
Keywords: anki
Author: patarapolw
Author-email: patarapolw@gmail.com
Requires-Python: >=3.7
Classifier: License :: OSI Approved :: MIT License
Classifier: Programming Language :: Python :: 3
Classifier: Programming Language :: Python :: 3.10
Classifier: Programming Language :: Python :: 3.7
Classifier: Programming Language :: Python :: 3.8
Classifier: Programming Language :: Python :: 3.9
